lektor_natural_language.py
lektor_natural_language-0.3.1.dist-info/LICENSE
lektor_natural_language-0.3.1.dist-info/METADATA
lektor_natural_language-0.3.1.dist-info/WHEEL
lektor_natural_language-0.3.1.dist-info/entry_points.txt
lektor_natural_language-0.3.1.dist-info/top_level.txt
lektor_natural_language-0.3.1.dist-info/RECORD
