Metadata-Version: 2.1
Name: lektor-natural-language
Version: 0.3.1
Summary: Adds NLTK based template filters.
Home-page: https://github.com/terminal-labs/lektor-natural-language
Author: Terminal Labs
Author-email: solutions@terminallabs.com
License: BSD-3-Clause
Keywords: Lektor plugin static-site nltk natrual-language jinja2 jinja filter
Platform: UNKNOWN
Classifier: Environment :: Plugins
Classifier: Environment :: Web Environment
Classifier: Framework :: Lektor
Classifier: License :: OSI Approved :: BSD License
Requires-Dist: nltk
Requires-Dist: rake-nltk
